odoo/addons/upgrade_analysis/README.rst
odoo/addons/upgrade_analysis/__init__.py
odoo/addons/upgrade_analysis/__manifest__.py
odoo/addons/upgrade_analysis/blacklist.py
odoo/addons/upgrade_analysis/compare.py
odoo/addons/upgrade_analysis/upgrade_log.py
odoo/addons/upgrade_analysis/i18n/es_AR.po
odoo/addons/upgrade_analysis/i18n/fr.po
odoo/addons/upgrade_analysis/i18n/it.po
odoo/addons/upgrade_analysis/i18n/upgrade_analysis.pot
odoo/addons/upgrade_analysis/i18n/zh_CN.po
odoo/addons/upgrade_analysis/models/__init__.py
odoo/addons/upgrade_analysis/models/ir_module_module.py
odoo/addons/upgrade_analysis/models/upgrade_analysis.py
odoo/addons/upgrade_analysis/models/upgrade_attribute.py
odoo/addons/upgrade_analysis/models/upgrade_comparison_config.py
odoo/addons/upgrade_analysis/models/upgrade_record.py
odoo/addons/upgrade_analysis/odoo_patch/__init__.py
odoo/addons/upgrade_analysis/odoo_patch/odoo_patch.py
odoo/addons/upgrade_analysis/odoo_patch/addons/__init__.py
odoo/addons/upgrade_analysis/odoo_patch/addons/mrp/__init__.py
odoo/addons/upgrade_analysis/odoo_patch/addons/stock/__init__.py
odoo/addons/upgrade_analysis/odoo_patch/odoo/__init__.py
odoo/addons/upgrade_analysis/odoo_patch/odoo/addons/__init__.py
odoo/addons/upgrade_analysis/odoo_patch/odoo/addons/base/__init__.py
odoo/addons/upgrade_analysis/odoo_patch/odoo/addons/base/models/__init__.py
odoo/addons/upgrade_analysis/odoo_patch/odoo/addons/base/models/ir_model.py
odoo/addons/upgrade_analysis/odoo_patch/odoo/orm/__init__.py
odoo/addons/upgrade_analysis/odoo_patch/odoo/orm/models.py
odoo/addons/upgrade_analysis/odoo_patch/odoo/orm/registry.py
odoo/addons/upgrade_analysis/odoo_patch/odoo/tools/__init__.py
odoo/addons/upgrade_analysis/odoo_patch/odoo/tools/convert.py
odoo/addons/upgrade_analysis/readme/CONTRIBUTORS.md
odoo/addons/upgrade_analysis/readme/DESCRIPTION.md
odoo/addons/upgrade_analysis/readme/ROADMAP.md
odoo/addons/upgrade_analysis/readme/USAGE.md
odoo_addon_upgrade_analysis-19.0.1.0.1.dist-info/METADATA
odoo_addon_upgrade_analysis-19.0.1.0.1.dist-info/WHEEL
odoo_addon_upgrade_analysis-19.0.1.0.1.dist-info/top_level.txt
odoo_addon_upgrade_analysis-19.0.1.0.1.dist-info/RECORD
