Metadata-Version: 2.1
Name: odoo-addon-upgrade_analysis
Version: 19.0.1.0.1
Requires-Dist: dataclasses
Requires-Dist: odoo==19.0.*
Requires-Dist: odoorpc
Requires-Dist: openupgradelib
Summary: Performs a difference analysis between modules installed on two different Odoo instances
Home-page: https://github.com/OCA/server-tools
License: AGPL-3
Author: Therp BV, Opener B.V., GRAP, Odoo Community Association (OCA)
Author-email: support@odoo-community.org
Classifier: Programming Language :: Python
Classifier: Framework :: Odoo
Classifier: Framework :: Odoo :: 19.0
Classifier: License :: OSI Approved :: GNU Affero General Public License v3
